streamlit_hgb/__init__.py
streamlit_hgb/frontend/build/asset-manifest.json
streamlit_hgb/frontend/build/bootstrap.min.css
streamlit_hgb/frontend/build/index.html
streamlit_hgb/frontend/build/precache-manifest.7a3701d7ea0d46d9859141ebc9cea3f7.js
streamlit_hgb/frontend/build/service-worker.js
streamlit_hgb/frontend/build/static/js/2.f83ab78a.chunk.js
streamlit_hgb/frontend/build/static/js/2.f83ab78a.chunk.js.LICENSE.txt
streamlit_hgb/frontend/build/static/js/2.f83ab78a.chunk.js.map
streamlit_hgb/frontend/build/static/js/main.e6772d3d.chunk.js
streamlit_hgb/frontend/build/static/js/main.e6772d3d.chunk.js.LICENSE.txt
streamlit_hgb/frontend/build/static/js/main.e6772d3d.chunk.js.map
streamlit_hgb/frontend/build/static/js/runtime-main.b0c38161.js
streamlit_hgb/frontend/build/static/js/runtime-main.b0c38161.js.map
streamlit_hgb-0.0.2.dist-info/LICENSE
streamlit_hgb-0.0.2.dist-info/METADATA
streamlit_hgb-0.0.2.dist-info/WHEEL
streamlit_hgb-0.0.2.dist-info/top_level.txt
streamlit_hgb-0.0.2.dist-info/RECORD
