Metadata-Version: 2.1
Name: streamlit-hgb
Version: 0.0.2
Summary: A streamlit component for a hybrid genome browser
Home-page: https://github.com/6br/streamlit_hgb
Author: 6br
Author-email: 
License: UNKNOWN
Platform: UNKNOWN
Requires-Python: >=3.6
Requires-Dist: streamlit (>=0.63)
Requires-Dist: pyyaml
Requires-Dist: Pillow (>=7.1.2)
